{"0unauthoris": ["20unauthoris"], "20unauthoris": ["20unauthoris"], "abas": ["databas"], "abras": ["abras"], "abus": ["abus"], "access": ["access", "inaccess"], "accessthes": ["accessthes"], "accus": ["accus"], "acteris": ["characteris"], "actis": ["practis"], "adbas": ["leadbas"], "address": ["address"], "addressthos": ["addressthos"], "admiss": ["admiss"], "advers": ["advers"], "advertis": ["advertis"], "advis": ["advis"], "agesimpos": ["damagesimpos"], "aglass": ["solaglass"], "aircas": ["staircas"], "ais": ["apprais", "rais"], "alis": ["nationalis", "realis", "specialis"], "alrespons": ["finalrespons"], "als": ["fals"], "altiesimpos": ["penaltiesimpos"], "amagesimpos": ["damagesimpos"], "amiliaris": ["familiaris"], "anchis": ["franchis"], "andis": ["merchandis"], "andus": ["andus"], "angestothos": ["changestothos"], "anis": ["organis"], "ans": ["expans"], "ansmiss": ["transmiss"], "apologis": ["apologis"], "apprais": ["apprais"], "aps": ["collaps", "elaps", "laps", "relaps"], "aracteris": ["characteris"], "arass": ["harass"], "ardless": ["regardless"], "areless": ["careless"], "aris": ["aris", "familiaris"], "armless": ["harmless"], "aros": ["aros"], "as": ["abras", "as", "ceas", "databas", "deceas", "decreas", "diseas", "eras", "increas", "invas", "isincreas", "leadbas", "leas", "occas", "ordiseas", "pleas", "plusincreas", "purchas", "releas", "staircas"], "asrefus": ["hasrefus"], "ass": ["class", "eyeglass", "glass", "harass", "pass", "solaglass", "trespass", "underpass"], "assess": ["assess", "reassess"], "asshous": ["glasshous"], "asthes": ["asthes"], "atabas": ["databas"], "ategoris": ["categoris"], "ates": ["operates"], "ationalis": ["nationalis"], "aus": ["becaus", "caus", "claus", "subclaus"], "authoris": ["20unauthoris", "authoris", "unauthoris"], "bas": ["databas", "leadbas"], "bclaus": ["subclaus"], "becaus": ["becaus"], "bmiss": ["submiss"], "bras": ["abras"], "brows": ["brows"], "burs": ["disburs", "reimburs"], "bus": ["abus"], "bvers": ["subvers"], "careless": ["careless"], "cas": ["occas", "staircas"], "categoris": ["categoris"], "caus": ["becaus", "caus"], "ccas": ["occas"], "ccess": ["access", "inaccess", "ofsuccess", "success", "unsuccess"], "ccessthes": ["accessthes"], "ccus": ["accus"], "ceas": ["ceas", "deceas"], "cens": ["licens", "vehicleslicens"], "cess": ["access", "concess", "excess", "inaccess", "necess", "ofsuccess", "process", "success", "unsuccess"], "cessthes": ["accessthes"], "chandis": ["merchandis"], "changestothos": ["changestothos"], "characteris": ["characteris"], "chas": ["purchas"], "chis": ["franchis"], "choos": ["choos"], "cialis": ["specialis"], "cious": ["conscious"], "cis": ["decis", "exercis", "precis"], "ckless": ["reckless"], "class": ["class"], "claus": ["claus", "subclaus"], "cleslicens": ["vehicleslicens"], "clos": ["disclos", "enclos"], "clus": ["conclus", "exclus", "inclus"], "cognis": ["recognis"], "collaps": ["collaps"], "collis": ["collis"], "collus": ["collus"], "commiss": ["commiss"], "compens": ["compens"], "compos": ["compos"], "comprehens": ["comprehens"], "compris": ["compris"], "compromis": ["compromis"], "concess": ["concess"], "conclus": ["conclus"], "conomis": ["economis"], "conscious": ["conscious"], "convers": ["convers"], "corros": ["corros"], "cours": ["cours", "recours"], "creas": ["decreas", "increas", "isincreas", "plusincreas"], "crisisrespons": ["crisisrespons"], "cross": ["cross"], "cteris": ["characteris"], "ctis": ["practis"], "curios": ["curios"], "cus": ["accus", "excus"], "cuss": ["discuss"], "damagesimpos": ["damagesimpos"], "databas": ["databas"], "dbas": ["leadbas"], "ddress": ["address"], "ddressthos": ["addressthos"], "deceas": ["deceas"], "decis": ["decis"], "decreas": ["decreas"], "defens": ["defens"], "derpass": ["underpass"], "dis": ["merchandis"], "disburs": ["disburs"], "disclos": ["disclos"], "discuss": ["discuss"], "diseas": ["diseas", "ordiseas"], "dismiss": ["dismiss"], "dispens": ["dispens"], "dispers": ["dispers"], "dispos": ["dispos"], "distress": ["distress"], "disus": ["disus"], "divis": ["divis"], "dless": ["groundless", "regardless"], "dmiss": ["admiss"], "dors": ["endors"], "dress": ["address", "dress"], "dressthos": ["addressthos"], "dryness": ["dryness"], "dss": ["dss"], "dus": ["andus"], "dvers": ["advers"], "dvertis": ["advertis"], "dvis": ["advis"], "eadbas": ["leadbas"], "ealis": ["realis"], "eas": ["ceas", "deceas", "decreas", "diseas", "increas", "isincreas", "leas", "ordiseas", "pleas", "plusincreas", "releas"], "eassess": ["reassess"], "ecaus": ["becaus"], "eceas": ["deceas"], "ecess": ["necess"], "ecialis": ["specialis"], "ecis": ["decis", "precis"], "eckless": ["reckless"], "ecognis": ["recognis"], "economis": ["economis"], "ecours": ["recours"], "ecreas": ["decreas"], "eenhous": ["greenhous"], "efens": ["defens"], "efus": ["hasrefus", "refus"], "egardless": ["regardless"], "egitimis": ["legitimis"], "eglass": ["eyeglass"], "egoris": ["categoris"], "ehens": ["comprehens", "prehens"], "ehicleslicens": ["vehicleslicens"], "eimburs": ["reimburs"], "elaps": ["elaps", "relaps"], "eleas": ["releas"], "eless": ["careless"], "elevis": ["televis"], "els": ["els"], "emis": ["premis"], "emiss": ["emiss"], "enaltiesimpos": ["penaltiesimpos"], "enclos": ["enclos"], "endors": ["endors"], "enhous": ["greenhous"], "ens": ["compens", "comprehens", "defens", "dispens", "expens", "extens", "lens", "licens", "offens", "pens", "prehens", "pretens", "suspens", "vehicleslicens"], "enterpris": ["enterpris"], "eophys": ["geophys"], "epossess": ["repossess"], "epres": ["misrepres", "repres"], "eras": ["eras"], "erates": ["operates"], "erchandis": ["merchandis"], "ercis": ["exercis"], "erious": ["serious"], "eris": ["characteris"], "ermiss": ["permiss"], "eros": ["eros"], "erpass": ["underpass"], "erpris": ["enterpris"], "ers": ["advers", "convers", "dispers", "revers", "subvers", "univers"], "ertis": ["advertis"], "ervis": ["supervis"], "erwis": ["otherwis"], "es": ["accessthes", "asthes", "misrepres", "operates", "repres"], "esimpos": ["damagesimpos", "penaltiesimpos"], "eslicens": ["vehicleslicens"], "espass": ["trespass"], "espons": ["crisisrespons", "finalrespons", "isrespons", "respons", "srespons"], "esris": ["givesris"], "ess": ["access", "address", "assess", "careless", "concess", "distress", "dress", "dryness", "excess", "express", "groundless", "harmless", "impress", "inaccess", "isless", "less", "necess", "ness", "ofsuccess", "orsuppress", "possess", "process", "profess", "progress", "reassess", "reckless", "regardless", "repossess", "stress", "success", "suppress", "unless", "unsuccess"], "essthes": ["accessthes"], "essthos": ["addressthos"], "estothos": ["changestothos"], "etens": ["pretens"], "evers": ["revers"], "evious": ["previous"], "evis": ["revis", "televis"], "ewis": ["likewis"], "excess": ["excess"], "exclus": ["exclus"], "excus": ["excus"], "exercis": ["exercis"], "expans": ["expans"], "expens": ["expens"], "explos": ["explos"], "expos": ["expos", "unexpos"], "express": ["express"], "extens": ["extens"], "eyeglass": ["eyeglass"], "fals": ["fals"], "familiaris": ["familiaris"], "fens": ["defens", "offens"], "fess": ["profess"], "ffens": ["offens"], "finalrespons": ["finalrespons"], "franchis": ["franchis"], "fsuccess": ["ofsuccess"], "fus": ["hasrefus", "refus"], "ganis": ["organis"], "gardless": ["regardless"], "geophys": ["geophys"], "gesimpos": ["damagesimpos"], "gestothos": ["changestothos"], "gis": ["apologis"], "gitimis": ["legitimis"], "givesris": ["givesris"], "glass": ["eyeglass", "glass", "solaglass"], "glasshous": ["glasshous"], "gnis": ["recognis"], "goris": ["categoris"], "greenhous": ["greenhous"], "gress": ["progress"], "gross": ["gross"], "groundless": ["groundless"], "handis": ["merchandis"], "hangestothos": ["changestothos"], "haracteris": ["characteris"], "harass": ["harass"], "harmless": ["harmless"], "has": ["purchas"], "hasrefus": ["hasrefus"], "hens": ["comprehens", "prehens"], "herwis": ["otherwis"], "hes": ["accessthes", "asthes"], "hicleslicens": ["vehicleslicens"], "his": ["franchis"], "hoos": ["choos"], "horis": ["20unauthoris", "authoris", "unauthoris"], "hors": ["hors"], "hos": ["addressthos", "changestothos"], "hous": ["glasshous", "greenhous", "hous"], "hys": ["geophys"], "ialis": ["specialis"], "iaris": ["familiaris"], "icens": ["licens", "vehicleslicens"], "icleslicens": ["vehicleslicens"], "iesimpos": ["penaltiesimpos"], "ikewis": ["likewis"], "iliaris": ["familiaris"], "ilis": ["utilis"], "imburs": ["reimburs"], "imis": ["legitimis", "minimis"], "impos": ["damagesimpos", "impos", "penaltiesimpos"], "impress": ["impress"], "inaccess": ["inaccess"], "inalrespons": ["finalrespons"], "inclus": ["inclus"], "increas": ["increas", "isincreas", "plusincreas"], "inimis": ["minimis"], "ins": ["intrins"], "intrins": ["intrins"], "intrus": ["intrus"], "invas": ["invas"], "ionalis": ["nationalis"], "ionis": ["ionis"], "ios": ["curios"], "ious": ["conscious", "previous", "serious"], "ircas": ["staircas"], "is": ["20unauthoris", "advertis", "advis", "apologis", "apprais", "aris", "authoris", "categoris", "characteris", "collis", "compris", "compromis", "decis", "divis", "economis", "enterpris", "exercis", "familiaris", "franchis", "givesris", "ionis", "is", "legitimis", "likewis", "merchandis", "minimis", "nationalis", "organis", "otherwis", "practis", "precis", "premis", "promis", "provis", "rais", "realis", "recognis", "revis", "specialis", "supervis", "televis", "unauthoris", "upris", "utilis"], "isburs": ["disburs"], "isclos": ["disclos"], "iscuss": ["discuss"], "iseas": ["diseas", "ordiseas"], "isincreas": ["isincreas"], "isisrespons": ["crisisrespons"], "isless": ["isless"], "ismiss": ["dismiss"], "ispens": ["dispens"], "ispers": ["dispers"], "ispos": ["dispos"], "isrepres": ["misrepres"], "isrespons": ["crisisrespons", "isrespons"], "iss": ["admiss", "commiss", "dismiss", "emiss", "miss", "omiss", "permiss", "submiss", "transmiss"], "istress": ["distress"], "isus": ["disus", "misus"], "itimis": ["legitimis"], "itsloss": ["itsloss"], "ivers": ["univers"], "ivesris": ["givesris"], "ivis": ["divis"], "kewis": ["likewis"], "kless": ["reckless"], "laglass": ["solaglass"], "laps": ["collaps", "elaps", "laps", "relaps"], "lass": ["class", "eyeglass", "glass", "solaglass"], "lasshous": ["glasshous"], "laus": ["claus", "subclaus"], "leadbas": ["leadbas"], "leas": ["leas", "pleas", "releas"], "legitimis": ["legitimis"], "lens": ["lens"], "leslicens": ["vehicleslicens"], "less": ["careless", "groundless", "harmless", "isless", "less", "reckless", "regardless", "unless"], "levis": ["televis"], "liaris": ["familiaris"], "licens": ["licens", "vehicleslicens"], "likewis": ["likewis"], "lis": ["collis", "nationalis", "realis", "specialis", "utilis"], "llaps": ["collaps"], "llis": ["collis"], "llus": ["collus"], "logis": ["apologis"], "los": ["disclos", "enclos", "explos"], "loss": ["itsloss", "loss"], "lrespons": ["finalrespons"], "ls": ["els", "fals"], "ltiesimpos": ["penaltiesimpos"], "lus": ["collus", "conclus", "exclus", "inclus"], "lusincreas": ["plusincreas"], "magesimpos": ["damagesimpos"], "mburs": ["reimburs"], "merchandis": ["merchandis"], "miliaris": ["familiaris"], "minimis": ["minimis"], "mis": ["compromis", "economis", "legitimis", "minimis", "premis", "promis"], "misrepres": ["misrepres"], "miss": ["admiss", "commiss", "dismiss", "emiss", "miss", "omiss", "permiss", "submiss", "transmiss"], "misus": ["misus"], "mless": ["harmless"], "mmiss": ["commiss"], "mpens": ["compens"], "mpos": ["compos", "damagesimpos", "impos", "penaltiesimpos"], "mprehens": ["comprehens"], "mpress": ["impress"], "mpris": ["compris"], "mpromis": ["compromis"], "naccess": ["inaccess"], "nalis": ["nationalis"], "nalrespons": ["finalrespons"], "naltiesimpos": ["penaltiesimpos"], "nationalis": ["nationalis"], "nauthoris": ["20unauthoris", "unauthoris"], "ncess": ["concess"], "nchis": ["franchis"], "nclos": ["enclos"], "nclus": ["conclus", "inclus"], "ncreas": ["increas", "isincreas", "plusincreas"], "nderpass": ["underpass"], "ndis": ["merchandis"], "ndless": ["groundless"], "ndors": ["endors"], "ndus": ["andus"], "necess": ["necess"], "ness": ["dryness", "ness"], "nexpos": ["unexpos"], "ngestothos": ["changestothos"], "nhous": ["greenhous"], "nimis": ["minimis"], "nis": ["ionis", "organis", "recognis"], "nivers": ["univers"], "nless": ["unless"], "nomis": ["economis"], "ns": ["compens", "comprehens", "crisisrespons", "defens", "dispens", "expans", "expens", "extens", "finalrespons", "intrins", "isrespons", "lens", "licens", "offens", "pens", "prehens", "pretens", "respons", "srespons", "suspens", "vehicleslicens"], "nscious": ["conscious"], "nsmiss": ["transmiss"], "nsuccess": ["unsuccess"], "nterpris": ["enterpris"], "ntrins": ["intrins"], "ntrus": ["intrus"], "nurs": ["nurs"], "nus": ["unus"], "nvas": ["invas"], "nvers": ["convers"], "occas": ["occas"], "ocess": ["process"], "ofess": ["profess"], "offens": ["offens"], "ofsuccess": ["ofsuccess"], "ogis": ["apologis"], "ognis": ["recognis"], "ogress": ["progress"], "olaglass": ["solaglass"], "ollaps": ["collaps"], "ollis": ["collis"], "ollus": ["collus"], "ologis": ["apologis"], "omis": ["compromis", "economis", "promis"], "omiss": ["omiss"], "ommiss": ["commiss"], "ompens": ["compens"], "ompos": ["compos"], "omprehens": ["comprehens"], "ompris": ["compris"], "ompromis": ["compromis"], "onalis": ["nationalis"], "oncess": ["concess"], "onclus": ["conclus"], "onis": ["ionis"], "onomis": ["economis"], "ons": ["crisisrespons", "finalrespons", "isrespons", "respons", "srespons"], "onscious": ["conscious"], "onvers": ["convers"], "oos": ["choos"], "operates": ["operates"], "ophys": ["geophys"], "opos": ["propos"], "ordiseas": ["ordiseas"], "organis": ["organis"], "oris": ["20unauthoris", "authoris", "categoris", "unauthoris"], "orros": ["corros"], "ors": ["endors", "hors"], "orsuppress": ["orsuppress"], "os": ["addressthos", "aros", "changestothos", "choos", "compos", "corros", "curios", "damagesimpos", "disclos", "dispos", "enclos", "eros", "explos", "expos", "impos", "penaltiesimpos", "propos", "purpos", "suppos", "unexpos"], "oss": ["cross", "gross", "itsloss", "loss"], "ossess": ["possess", "repossess"], "otherwis": ["otherwis"], "othos": ["changestothos"], "oundless": ["groundless"], "ours": ["cours", "recours"], "ous": ["conscious", "glasshous", "greenhous", "hous", "previous", "serious", "spous"], "ovis": ["provis"], "ows": ["brows"], "pans": ["expans"], "pass": ["pass", "trespass", "underpass"], "pecialis": ["specialis"], "penaltiesimpos": ["penaltiesimpos"], "pens": ["compens", "dispens", "expens", "pens", "suspens"], "perates": ["operates"], "permiss": ["permiss"], "pers": ["dispers"], "pervis": ["supervis"], "phys": ["geophys"], "pleas": ["pleas"], "plos": ["explos"], "plusincreas": ["plusincreas"], "pologis": ["apologis"], "pons": ["crisisrespons", "finalrespons", "isrespons", "respons", "srespons"], "pos": ["compos", "damagesimpos", "dispos", "expos", "impos", "penaltiesimpos", "propos", "purpos", "suppos", "unexpos"], "possess": ["possess", "repossess"], "pous": ["spous"], "ppos": ["suppos"], "pprais": ["apprais"], "ppress": ["orsuppress", "suppress"], "practis": ["practis"], "prais": ["apprais"], "precis": ["precis"], "prehens": ["comprehens", "prehens"], "premis": ["premis"], "pres": ["misrepres", "repres"], "press": ["express", "impress", "orsuppress", "suppress"], "pretens": ["pretens"], "previous": ["previous"], "pris": ["compris", "enterpris", "upris"], "process": ["process"], "profess": ["profess"], "progress": ["progress"], "promis": ["compromis", "promis"], "propos": ["propos"], "provis": ["provis"], "ps": ["collaps", "elaps", "laps", "relaps"], "purchas": ["purchas"], "purpos": ["purpos"], "racteris": ["characteris"], "ractis": ["practis"], "rais": ["apprais", "rais"], "ranchis": ["franchis"], "ransmiss": ["transmiss"], "ras": ["abras", "eras"], "rass": ["harass"], "rates": ["operates"], "rcas": ["staircas"], "rchandis": ["merchandis"], "rchas": ["purchas"], "rcis": ["exercis"], "rdiseas": ["ordiseas"], "rdless": ["regardless"], "realis": ["realis"], "reas": ["decreas", "increas", "isincreas", "plusincreas"], "reassess": ["reassess"], "recis": ["precis"], "reckless": ["reckless"], "recognis": ["recognis"], "recours": ["recours"], "reenhous": ["greenhous"], "refus": ["hasrefus", "refus"], "regardless": ["regardless"], "rehens": ["comprehens", "prehens"], "reimburs": ["reimburs"], "relaps": ["relaps"], "releas": ["releas"], "reless": ["careless"], "remis": ["premis"], "repossess": ["repossess"], "repres": ["misrepres", "repres"], "res": ["misrepres", "repres"], "respass": ["trespass"], "respons": ["crisisrespons", "finalrespons", "isrespons", "respons", "srespons"], "ress": ["address", "distress", "dress", "express", "impress", "orsuppress", "progress", "stress", "suppress"], "ressthos": ["addressthos"], "retens": ["pretens"], "revers": ["revers"], "revious": ["previous"], "revis": ["revis"], "rganis": ["organis"], "rins": ["intrins"], "rios": ["curios"], "rious": ["serious"], "ris": ["20unauthoris", "aris", "authoris", "categoris", "characteris", "compris", "enterpris", "familiaris", "givesris", "unauthoris", "upris"], "risisrespons": ["crisisrespons"], "rmiss": ["permiss"], "rmless": ["harmless"], "rocess": ["process"], "rofess": ["profess"], "rogress": ["progress"], "romis": ["compromis", "promis"], "ropos": ["propos"], "ros": ["aros", "corros", "eros"], "ross": ["cross", "gross"], "roundless": ["groundless"], "rovis": ["provis"], "rows": ["brows"], "rpass": ["underpass"], "rpos": ["purpos"], "rpris": ["enterpris"], "rros": ["corros"], "rs": ["advers", "convers", "cours", "disburs", "dispers", "endors", "hors", "nurs", "recours", "reimburs", "revers", "subvers", "univers"], "rsuppress": ["orsuppress"], "rtis": ["advertis"], "rus": ["intrus"], "rvis": ["supervis"], "rwis": ["otherwis"], "ryness": ["dryness"], "s": ["20unauthoris", "abras", "abus", "access", "accessthes", "accus", "address", "addressthos", "admiss", "advers", "advertis", "advis", "andus", "apologis", "apprais", "aris", "aros", "as", "assess", "asthes", "authoris", "becaus", "brows", "careless", "categoris", "caus", "ceas", "changestothos", "characteris", "choos", "class", "claus", "collaps", "collis", "collus", "commiss", "compens", "compos", "comprehens", "compris", "compromis", "concess", "conclus", "conscious", "convers", "corros", "cours", "crisisrespons", "cross", "curios", "damagesimpos", "databas", "deceas", "decis", "decreas", "defens", "disburs", "disclos", "discuss", "diseas", "dismiss", "dispens", "dispers", "dispos", "distress", "disus", "divis", "dress", "dryness", "dss", "economis", "elaps", "els", "emiss", "enclos", "endors", "enterpris", "eras", "eros", "excess", "exclus", "excus", "exercis", "expans", "expens", "explos", "expos", "express", "extens", "eyeglass", "fals", "familiaris", "finalrespons", "franchis", "geophys", "givesris", "glass", "glasshous", "greenhous", "gross", "groundless", "harass", "harmless", "hasrefus", "hors", "hous", "impos", "impress", "inaccess", "inclus", "increas", "intrins", "intrus", "invas", "ionis", "is", "isincreas", "isless", "isrespons", "itsloss", "laps", "leadbas", "leas", "legitimis", "lens", "less", "licens", "likewis", "loss", "merchandis", "minimis", "misrepres", "miss", "misus", "nationalis", "necess", "ness", "nurs", "occas", "offens", "ofsuccess", "omiss", "operates", "ordiseas", "organis", "orsuppress", "otherwis", "pass", "penaltiesimpos", "pens", "permiss", "pleas", "plusincreas", "possess", "practis", "precis", "prehens", "premis", "pretens", "previous", "process", "profess", "progress", "promis", "propos", "provis", "purchas", "purpos", "rais", "realis", "reassess", "reckless", "recognis", "recours", "refus", "regardless", "reimburs", "relaps", "releas", "repossess", "repres", "respons", "revers", "revis", "s", "serious", "solaglass", "specialis", "spous", "srespons", "staircas", "stress", "subclaus", "submiss", "subvers", "success", "supervis", "suppos", "suppress", "suspens", "televis", "transmiss", "trespass", "unauthoris", "underpass", "unexpos", "univers", "unless", "unsuccess", "unus", "upris", "us", "utilis", "vehicleslicens"], "sburs": ["disburs"], "scious": ["conscious"], "sclos": ["disclos"], "scuss": ["discuss"], "seas": ["diseas", "ordiseas"], "serious": ["serious"], "sess": ["assess", "possess", "reassess", "repossess"], "shous": ["glasshous"], "simpos": ["damagesimpos", "penaltiesimpos"], "sincreas": ["isincreas", "plusincreas"], "sisrespons": ["crisisrespons"], "sless": ["isless"], "slicens": ["vehicleslicens"], "sloss": ["itsloss"], "smiss": ["dismiss", "transmiss"], "solaglass": ["solaglass"], "spass": ["trespass"], "specialis": ["specialis"], "spens": ["dispens", "suspens"], "spers": ["dispers"], "spons": ["crisisrespons", "finalrespons", "isrespons", "respons", "srespons"], "spos": ["dispos"], "spous": ["spous"], "srefus": ["hasrefus"], "srepres": ["misrepres"], "srespons": ["crisisrespons", "isrespons", "srespons"], "sris": ["givesris"], "ss": ["access", "address", "admiss", "assess", "careless", "class", "commiss", "concess", "cross", "discuss", "dismiss", "distress", "dress", "dryness", "dss", "emiss", "excess", "express", "eyeglass", "glass", "gross", "groundless", "harass", "harmless", "impress", "inaccess", "isless", "itsloss", "less", "loss", "miss", "necess", "ness", "ofsuccess", "omiss", "orsuppress", "pass", "permiss", "possess", "process", "profess", "progress", "reassess", "reckless", "regardless", "repossess", "solaglass", "stress", "submiss", "success", "suppress", "transmiss", "trespass", "underpass", "unless", "unsuccess"], "ssess": ["assess", "possess", "reassess", "repossess"], "sshous": ["glasshous"], "ssthes": ["accessthes"], "ssthos": ["addressthos"], "staircas": ["staircas"], "sthes": ["accessthes", "asthes"], "sthos": ["addressthos"], "stothos": ["changestothos"], "stress": ["distress", "stress"], "subclaus": ["subclaus"], "submiss": ["submiss"], "subvers": ["subvers"], "success": ["ofsuccess", "success", "unsuccess"], "supervis": ["supervis"], "suppos": ["suppos"], "suppress": ["orsuppress", "suppress"], "sus": ["disus", "misus"], "suspens": ["suspens"], "tabas": ["databas"], "taircas": ["staircas"], "tegoris": ["categoris"], "televis": ["televis"], "tens": ["extens", "pretens"], "teris": ["characteris"], "terpris": ["enterpris"], "tes": ["operates"], "therwis": ["otherwis"], "thes": ["accessthes", "asthes"], "thoris": ["20unauthoris", "authoris", "unauthoris"], "thos": ["addressthos", "changestothos"], "tiesimpos": ["penaltiesimpos"], "tilis": ["utilis"], "timis": ["legitimis"], "tionalis": ["nationalis"], "tis": ["advertis", "practis"], "tothos": ["changestothos"], "transmiss": ["transmiss"], "trespass": ["trespass"], "tress": ["distress", "stress"], "trins": ["intrins"], "trus": ["intrus"], "tsloss": ["itsloss"], "ubclaus": ["subclaus"], "ubmiss": ["submiss"], "ubvers": ["subvers"], "uccess": ["ofsuccess", "success", "unsuccess"], "unauthoris": ["20unauthoris", "unauthoris"], "underpass": ["underpass"], "undless": ["groundless"], "unexpos": ["unexpos"], "univers": ["univers"], "unless": ["unless"], "unsuccess": ["unsuccess"], "unus": ["unus"], "upervis": ["supervis"], "uppos": ["suppos"], "uppress": ["orsuppress", "suppress"], "upris": ["upris"], "urchas": ["purchas"], "urios": ["curios"], "urpos": ["purpos"], "urs": ["cours", "disburs", "nurs", "recours", "reimburs"], "us": ["abus", "accus", "andus", "becaus", "caus", "claus", "collus", "conclus", "conscious", "disus", "exclus", "excus", "glasshous", "greenhous", "hasrefus", "hous", "inclus", "intrus", "misus", "previous", "refus", "serious", "spous", "subclaus", "unus", "us"], "usincreas": ["plusincreas"], "uspens": ["suspens"], "uss": ["discuss"], "uthoris": ["20unauthoris", "authoris", "unauthoris"], "utilis": ["utilis"], "vas": ["invas"], "vehicleslicens": ["vehicleslicens"], "vers": ["advers", "convers", "revers", "subvers", "univers"], "vertis": ["advertis"], "vesris": ["givesris"], "vious": ["previous"], "vis": ["advis", "divis", "provis", "revis", "supervis", "televis"], "wis": ["likewis", "otherwis"], "ws": ["brows"], "xcess": ["excess"], "xclus": ["exclus"], "xcus": ["excus"], "xercis": ["exercis"], "xpans": ["expans"], "xpens": ["expens"], "xplos": ["explos"], "xpos": ["expos", "unexpos"], "xpress": ["express"], "xtens": ["extens"], "yeglass": ["eyeglass"], "yness": ["dryness"], "ys": ["geophys"]}